setup.py
gtfslib/__init__.py
gtfslib/converter.py
gtfslib/csvgtfs.py
gtfslib/dao.py
gtfslib/gtfsdbloader.py
gtfslib/model.py
gtfslib/orm.py
gtfslib/spatial.py
gtfslib/utils.py
gtfslib.egg-info/PKG-INFO
gtfslib.egg-info/SOURCES.txt
gtfslib.egg-info/dependency_links.txt
gtfslib.egg-info/entry_points.txt
gtfslib.egg-info/requires.txt
gtfslib.egg-info/top_level.txt
gtfsplugins/__init__.py
gtfsplugins/decret_2015_1610.py
gtfsplugins/demoplugin.py
gtfsplugins/export.py
gtfsplugins/frequencies.py
gtfsplugins/gtfsrun.py
gtfsplugins/prettycsv.py
gtfsplugins/shpexport.py
gtfsplugins/tripsperday.py
test/__init__.py
test/test_all_gtfs.py
test/test_autojoin.py
test/test_broken.py
test/test_dao.py
test/test_demo.py
test/test_dummy.py
test/test_gtfs.py
test/test_mini.py
test/test_model.py
test/test_prettyprint.py
test/test_spatial.py
test/test_utils.py