Metadata-Version: 1.1
Name: gtfslib
Version: 1.0.0
Summary: GTFS database library
Home-page: https://github.com/afimb/gtfslib-python
Author: AFIMB / CEREMA / MECATRAN
Author-email: laurent.gregoire@mecatran.com
License: GPLv3
Keywords: GTFS transit
Platform: UNKNOWN
Classifier: Development Status :: 3 - Alpha
Classifier: Environment :: Console
Classifier: Operating System :: OS Independent
Classifier: Intended Audience :: Developers
Classifier: Topic :: Scientific/Engineering :: GIS
Classifier: License :: OSI Approved :: GNU General Public License v3 (GPLv3)
Classifier: Programming Language :: Python :: 2
Classifier: Programming Language :: Python :: 3
